karrio/mappers/mydhl/__init__.py
karrio/mappers/mydhl/mapper.py
karrio/mappers/mydhl/proxy.py
karrio/mappers/mydhl/settings.py
karrio/plugins/mydhl/__init__.py
karrio/providers/mydhl/__init__.py
karrio/providers/mydhl/address.py
karrio/providers/mydhl/document.py
karrio/providers/mydhl/error.py
karrio/providers/mydhl/rate.py
karrio/providers/mydhl/tracking.py
karrio/providers/mydhl/units.py
karrio/providers/mydhl/utils.py
karrio/providers/mydhl/pickup/__init__.py
karrio/providers/mydhl/pickup/cancel.py
karrio/providers/mydhl/pickup/create.py
karrio/providers/mydhl/pickup/update.py
karrio/providers/mydhl/shipment/__init__.py
karrio/providers/mydhl/shipment/create.py
karrio/schemas/mydhl/__init__.py
karrio/schemas/mydhl/address_validation_request.py
karrio/schemas/mydhl/address_validation_response.py
karrio/schemas/mydhl/error_response.py
karrio/schemas/mydhl/pickup_cancel_request.py
karrio/schemas/mydhl/pickup_cancel_response.py
karrio/schemas/mydhl/pickup_create_request.py
karrio/schemas/mydhl/pickup_create_response.py
karrio/schemas/mydhl/pickup_update_request.py
karrio/schemas/mydhl/pickup_update_response.py
karrio/schemas/mydhl/rate_request.py
karrio/schemas/mydhl/rate_response.py
karrio/schemas/mydhl/shipment_cancel_request.py
karrio/schemas/mydhl/shipment_cancel_response.py
karrio/schemas/mydhl/shipment_request.py
karrio/schemas/mydhl/shipment_response.py
karrio/schemas/mydhl/tracking_request.py
karrio/schemas/mydhl/tracking_response.py
karrio_mydhl-2026.1.4.dist-info/METADATA
karrio_mydhl-2026.1.4.dist-info/WHEEL
karrio_mydhl-2026.1.4.dist-info/entry_points.txt
karrio_mydhl-2026.1.4.dist-info/top_level.txt
karrio_mydhl-2026.1.4.dist-info/RECORD
